[
  {
    "id": "nats-suite-server-example",
    "type": "tab",
    "label": "NATS Server Configuration Example",
    "disabled": false,
    "info": "Beispiel für NATS Server Konfiguration mit verschiedenen Authentifizierungsmethoden und TLS/SSL"
  },
  {
    "id": "nats-suite-server-basic",
    "type": "nats-suite-server",
    "z": "nats-suite-server-example",
    "name": "Basic NATS Server",
    "server": "localhost:4222",
    "timeout": 10000,
    "pingInterval": 30000,
    "maxPingOut": 3,
    "authMethod": "userpass",
    "enableTLS": false,
    "tlsRejectUnauthorized": true,
    "tlsCaFile": "",
    "tlsCertFile": "",
    "tlsKeyFile": "",
    "x": 200,
    "y": 100,
    "wires": []
  },
  {
    "id": "nats-suite-server-tls",
    "type": "nats-suite-server",
    "z": "nats-suite-server-example",
    "name": "TLS NATS Server",
    "server": "nats.example.com:4222",
    "timeout": 10000,
    "pingInterval": 30000,
    "maxPingOut": 3,
    "authMethod": "token",
    "enableTLS": true,
    "tlsRejectUnauthorized": true,
    "tlsCaFile": "/path/to/ca.pem",
    "tlsCertFile": "/path/to/client.pem",
    "tlsKeyFile": "/path/to/client-key.pem",
    "x": 200,
    "y": 200,
    "wires": []
  },
  {
    "id": "nats-suite-server-jwt",
    "type": "nats-suite-server",
    "z": "nats-suite-server-example",
    "name": "JWT NATS Server",
    "server": "nats-auth.example.com:4222",
    "timeout": 10000,
    "pingInterval": 30000,
    "maxPingOut": 3,
    "authMethod": "jwt",
    "enableTLS": true,
    "tlsRejectUnauthorized": true,
    "tlsCaFile": "/path/to/ca.pem",
    "tlsCertFile": "/path/to/client.pem",
    "tlsKeyFile": "/path/to/client-key.pem",
    "x": 200,
    "y": 300,
    "wires": []
  },
  {
    "id": "comment-1",
    "type": "comment",
    "z": "nats-suite-server-example",
    "name": "NATS Server Konfigurationen",
    "info": "Verschiedene NATS Server Konfigurationen:\n\n1. **Basic Server**: Einfache Verbindung ohne TLS\n2. **TLS Server**: Sichere Verbindung mit TLS/SSL\n3. **JWT Server**: Authentifizierung mit JWT + NKey\n\n**Wichtige Einstellungen:**\n- **Auth Method**: userpass, token, jwt, nkey, none\n- **TLS/SSL**: Für Produktionsumgebungen empfohlen\n- **Credentials**: Werden sicher in Node-RED gespeichert",
    "x": 200,
    "y": 40,
    "wires": []
  }
]

